README.md
setup.py
ccommon/__init__.py
ccommon/html.py
ccommon/httpSimple.py
ccommon/jsonParse.py
ccommon/log.py
ccommon/monitor.py
ccommon/report.py
ccommon/util.py
ccommon.egg-info/PKG-INFO
ccommon.egg-info/SOURCES.txt
ccommon.egg-info/dependency_links.txt
ccommon.egg-info/top_level.txt
ccommon.egg-info/zip-safe
db/__init__.py
db/hive.py
db/influxdb.py
db/mongo.py
db/mysql.py
db/redisdb.py
mail/__init__.py
mail/smtp.py
tapdApi/__init__.py
tapdApi/tapd.py
tapdApi/tapd_bug.py
tapdApi/tapd_param.py
tapdApi/tapd_story.py
tapdApi/tapd_task.py
tapdApi/tapd_test_plan.py