Metadata-Version: 1.1
Name: ccommon
Version: 1.5.5
Summary: 新增tapd计划
Home-page: http://none
Author: chenjw
Author-email: **@qq.com
License: MIT
Platform: UNKNOWN
Classifier: License :: OSI Approved :: MIT License
Classifier: Programming Language :: Python
Classifier: Intended Audience :: Developers
Classifier: Operating System :: OS Independent
